README.txt
setup.cfg
setup.py
LinguaPlus/__init__.py
LinguaPlus/handlers.py
LinguaPlus/outdate.py
LinguaPlus/tests.py
LinguaPlus.egg-info/PKG-INFO
LinguaPlus.egg-info/SOURCES.txt
LinguaPlus.egg-info/dependency_links.txt
LinguaPlus.egg-info/entry_points.txt
LinguaPlus.egg-info/not-zip-safe
LinguaPlus.egg-info/requires.txt
LinguaPlus.egg-info/top_level.txt
LinguaPlus/browser/__init__.py
LinguaPlus/browser/sidebyside.py