Metadata-Version: 1.0
Name: LinguaPlus
Version: 0.4
Summary: Content actions and plone.app.iterate support for LinguaPlone.
Home-page: http://bitbucket.org/dholth/linguaplus
Author: Daniel Holth
Author-email: daniel.holth@exac.com
License: GPL
Platform: UNKNOWN
Classifier: Framework :: Plone
Classifier: Programming Language :: Python
Classifier: Topic :: Software Development :: Libraries :: Python Modules
